{
  "circles": [
    {
      "id": 0,
      "name": "airou -プログラミングサークル-",
      "about": "プログラミング学習、教育",
      "eyecatch": "https://media2.tokyodisneyresort.jp/home/tdl/top/mainL_201910_01.jpg",
      "catchCopy": "プログラミング学習・教育",
      "description": "string",
      "types": [
        {
          "id": 1,
          "name": "葛飾"
        }
      ],
      "category": {
        "id": 3,
        "name": "文化系"
      }
    }, {
      "id": 1,
      "name": "airou",
      "about": "プログラミング学習、教育",
      "eyecatch": "https://media2.tokyodisneyresort.jp/home/tdl/top/mainL_201910_01.jpg",
      "catchCopy": "string",
      "description": "string",
      "types": [
        {
          "id": 1,
          "name": "葛飾"
        }
      ],
      "category": {
        "id": 3,
        "name": "文化系"
      }
    }, {
      "id": 2,
      "name": "airou",
      "about": "プログラミング学習、教育",
      "eyecatch": "https://media2.tokyodisneyresort.jp/home/tdl/top/mainL_201910_01.jpg",
      "catchCopy": "string",
      "description": "string",
      "types": [
        {
          "id": 1,
          "name": "葛飾"
        }
      ],
      "category": {
        "id": 3,
        "name": "文化系"
      }
    }
  ]
}
